Metadata-Version: 2.1
Name: hoster
Version: 0.0.2
Summary: hoster is a python module that hosts code
Home-page: https://github.com/henos1029/hoster
Author: henos
Author-email: henos1029@gmail.com
License: MIT
Keywords: alive,keep alive,henos,host,hoster
Platform: UNKNOWN
